CHANGES.txt
COPYRIGHT.txt
LICENSE.txt
README.txt
bootstrap.py
buildout.cfg
setup.py
src/z3c/__init__.py
src/z3c.locales.egg-info/PKG-INFO
src/z3c.locales.egg-info/SOURCES.txt
src/z3c.locales.egg-info/dependency_links.txt
src/z3c.locales.egg-info/namespace_packages.txt
src/z3c.locales.egg-info/not-zip-safe
src/z3c.locales.egg-info/requires.txt
src/z3c.locales.egg-info/top_level.txt
src/z3c/locales/__init__.py
src/z3c/locales/configure.zcml
src/z3c/locales/extract.zcml
src/z3c/locales/z3c.pot
src/z3c/locales/de/LC_MESSAGES/z3c.po