Metadata-Version: 1.0
Name: z3c.locales
Version: 0.3.0
Summary: Shared z3c domain translations
Home-page: http://pypi.python.org/pypi/z3c.locales
Author: Zope Foundation and Contributors
Author-email: zope-dev@zope.org
License: ZPL 2.1
Keywords: Zope z3c locale locales i18n internationalisation
Platform: UNKNOWN
Classifier: Development Status :: 4 - Beta
Classifier: Environment :: Web Environment
Classifier: Intended Audience :: Developers
Classifier: License :: OSI Approved :: Zope Public License
Classifier: Programming Language :: Python
Classifier: Natural Language :: English
Classifier: Natural Language :: German
Classifier: Operating System :: OS Independent
Classifier: Topic :: Internet :: WWW/HTTP
Classifier: Framework :: Zope3
